atr_adaptive_laguerre/__init__.py
atr_adaptive_laguerre/backtesting_adapter.py
atr_adaptive_laguerre/backtesting_models.py
atr_adaptive_laguerre/py.typed
atr_adaptive_laguerre/core/__init__.py
atr_adaptive_laguerre/core/adaptive.py
atr_adaptive_laguerre/core/atr.py
atr_adaptive_laguerre/core/laguerre_filter.py
atr_adaptive_laguerre/core/laguerre_rsi.py
atr_adaptive_laguerre/core/true_range.py
atr_adaptive_laguerre/data/__init__.py
atr_adaptive_laguerre/data/binance_adapter.py
atr_adaptive_laguerre/data/schema.py
atr_adaptive_laguerre/features/__init__.py
atr_adaptive_laguerre/features/atr_adaptive_rsi.py
atr_adaptive_laguerre/features/base.py
atr_adaptive_laguerre/features/cross_interval.py
atr_adaptive_laguerre/features/feature_expander.py
atr_adaptive_laguerre/features/multi_interval.py
atr_adaptive_laguerre/features/redundancy_filter.py
atr_adaptive_laguerre/utils/__init__.py
atr_adaptive_laguerre/validation/__init__.py
atr_adaptive_laguerre/validation/information_coefficient.py
atr_adaptive_laguerre/validation/non_anticipative.py
atr_adaptive_laguerre/validation/ood_robustness.py
atr_adaptive_laguerre-2.0.3.dist-info/METADATA
atr_adaptive_laguerre-2.0.3.dist-info/WHEEL
atr_adaptive_laguerre-2.0.3.dist-info/RECORD
