Metadata-Version: 2.4
Name: atr-adaptive-laguerre
Version: 2.0.3
Summary: ATR-adaptive Laguerre RSI for non-anticipative feature engineering in seq-2-seq forecasting
Project-URL: Repository, https://github.com/terrylica/atr-adaptive-laguerre
Project-URL: Documentation, https://github.com/terrylica/atr-adaptive-laguerre/blob/main/docs/README.md
Author: Eon Labs Ltd.
Keywords: atr,features,laguerre,rsi,seq2seq,trading,volatility
Classifier: Development Status :: 3 - Alpha
Classifier: Intended Audience :: Financial and Insurance Industry
Classifier: Programming Language :: Python :: 3.10
Classifier: Programming Language :: Python :: 3.11
Classifier: Programming Language :: Python :: 3.12
Classifier: Programming Language :: Python :: 3.13
Classifier: Topic :: Scientific/Engineering :: Artificial Intelligence
Requires-Python: >=3.10
Requires-Dist: httpx>=0.27
Requires-Dist: numba>=0.59
Requires-Dist: numpy>=1.26
Requires-Dist: orjson>=3.10
Requires-Dist: pandas>=2.0
Requires-Dist: platformdirs>=4.0
Requires-Dist: pydantic>=2.0
Requires-Dist: scipy>=1.10
Provides-Extra: data
Requires-Dist: gapless-crypto-data>=2.11.0; extra == 'data'
Requires-Dist: pyarrow>=15.0; extra == 'data'
Provides-Extra: dev
Requires-Dist: hypothesis>=6.0; extra == 'dev'
Requires-Dist: mypy>=1.8; extra == 'dev'
Requires-Dist: pytest-cov>=4.1; extra == 'dev'
Requires-Dist: pytest>=8.0; extra == 'dev'
Requires-Dist: ruff>=0.3; extra == 'dev'
